nyxfall/__init__.py
nyxfall/__main__.py
nyxfall/card.py
nyxfall/card_face.py
nyxfall/scryfall_requester.py
nyxfall-1.0.0.dist-info/licenses/LICENSE
nyxfall-1.0.0.dist-info/METADATA
nyxfall-1.0.0.dist-info/WHEEL
nyxfall-1.0.0.dist-info/entry_points.txt
nyxfall-1.0.0.dist-info/top_level.txt
nyxfall-1.0.0.dist-info/RECORD
