Metadata-Version: 2.4
Name: nyxfall
Version: 1.0.0
Summary: A command-line Magic: the Gathering card search
Author-email: Avery Abrahams-Whitehead <averywhthead@gmail.com>
Project-URL: Homepage, https://github.com/avery-whitehead/nyxfall
Project-URL: Issues, https://github.com/avery-whitehead/nyxfall/issues
Keywords: mtg,cards,magic,gathering,scryfall
Classifier: Programming Language :: Python :: 3
Classifier: Operating System :: OS Independent
Classifier: License :: OSI Approved :: MIT License
Classifier: Development Status :: 4 - Beta
Requires-Python: >=3.12.3
License-File: LICENSE
Requires-Dist: requests
Requires-Dist: pytest
Requires-Dist: beaupy
Requires-Dist: build
Requires-Dist: twine
Dynamic: license-file
